[{"epr":"50 NL ","time":"00:29.46","age":"(39 ans)","place":"(FRA)CACHAN","date":"08/01/2017"},{"epr":"100 NL ","time":"01:08.21","age":"(38 ans)","place":"(FRA)LA GARENNE-COLOMBES","date":"13/03/2016"},{"epr":"1500 NL ","time":"21:17.41","age":"(39 ans)","place":"(FRA)CACHAN","date":"07/01/2017"},{"epr":"50 Bra. ","time":"00:38.62","age":"(38 ans)","place":"(FRA)VILLEPINTE","date":"16/12/2016"},{"epr":"100 Bra. ","time":"01:24.68","age":"(39 ans)","place":"(FRA)CACHAN","date":"08/01/2017"},{"epr":"50 Pap. ","time":"00:31.15","age":"(39 ans)","place":"(FRA)CACHAN","date":"08/01/2017"},{"epr":"100 Pap. ","time":"01:08.93","age":"(38 ans)","place":"(FRA)VILLEPINTE","date":"16/12/2016"},{"epr":"200 Pap. ","time":"02:57.70","age":"(39 ans)","place":"(FRA)PUTEAUX","date":"05/11/2016"},{"epr":"50 NL ","time":"00:30.32","age":"(38 ans)","place":"(LUX)LUXEMBOURG","date":"16/10/2016"},{"epr":"100 NL ","time":"01:08.67","age":"(38 ans)","place":"(LUX)LUXEMBOURG","date":"15/10/2016"},{"epr":"50 Pap. ","time":"00:31.42","age":"(38 ans)","place":"(LUX)LUXEMBOURG","date":"16/10/2016"},{"epr":"100 Pap. ","time":"01:12.69","age":"(38 ans)","place":"(LUX)LUXEMBOURG","date":"15/10/2016"}]